Workbook

Sheet Инструкция
B1: Калькулятор юнит-экономики: онлайн-магазин женских сумок, Ташкент
B2: Связан с бизнес-планом: все стартовые цифры совпадают с базовым сценарием плана (октябрь 2026).
B4: Как пользоваться
B5: 1. «Допущения» — курсы, пошлина, доставка, реклама, канал продаж, постоянные расходы. Меняйте под свои данные.
B6: 2. «Юнит-экономика» — по каждой модели: закупка в юанях, розничная цена, доля в продажах. Итог — сколько остаётся с заказа и точка безубыточности.
B7: 3. «Прогноз» — введите план заказов и постоянных расходов по месяцам: увидите прибыль по месяцам и окупаемость стартовых вложений.
B8: 4. «Чувствительность» — сколько заказов в месяц нужно при другой цене и другой стоимости рекламы.
B10: Обозначения
B11: Синий текст на жёлтом фоне — ячейки для ввода. Синий текст без заливки — тоже ввод, но второстепенный.
B12: Чёрный текст — формулы, не трогайте. Зелёный — ссылка на лист «Допущения».
B13: Голубая заливка — ключевые итоги. Красный текст — убыток или предупреждение.
B15: Что проверить в первую очередь
... B26: Комиссии и логистика Uzum: billz.io/blog/marketplace-uzbekistana-kakoy-vybrat

Sheet Допущения
A1: Допущения: общие для всех моделей
A2: Синие цифры на жёлтом фоне — вводите свои значения. Остальные листы пересчитаются сами.
A4: Параметр | B4: Значение | C4: Единица | D4: Источник / комментарий
A5: Курсы валют
A6: Курс доллара | B6: 11800 | C6: сум за $1 | D6: ЦБ Узбекистана на 01.10.2026: 11 808,76 сума (uz.kursiv.media). Обновляйте перед каждой закупкой.
A7: Курс юаня | B7: 1650 | C7: сум за ¥1 | D7: Допущение: курс доллара / ~7,15. Уточните курс у байера или банка перед оплатой фабрике.
A9: Закупка и ввоз
A10: Комиссия байера | B10: 0.05 | C10: % от закупки | D10: Допущение. Обычная ставка байера — несколько процентов от суммы заказа.
A11: Упаковка: пыльник, коробка, карточка | B11: 14 | C11: ¥ за сумку | D11: Допущение: заказ упаковки у той же фабрики.
A12: Доставка Китай → Ташкент | B12: 3.4 | C12: $ за сумку | D12: Допущение: около 1 кг с упаковкой, автодоставка с документами («белый» ввоз).
A13: Таможенная пошлина | B13: 0.2 | C13: % от тамож. стоимости | D13: Рабочее допущение. В 2018 году на дамские сумки (код 4202) было 15%, но не менее $1,5 за шт., обсуждалось повышение до 20% (norma.uz). Актуальную ставку подтвердит брокер.
A14: Минимальная пошлина | B14: 1.5 | C14: $ за сумку | D14: Из той же нормы 2018 года (norma.uz). Если пошлина по % меньше — берётся минимум.
A15: НДС при ввозе | B15: 0.12 | C15: % | D15: 12% от таможенной стоимости с пошлиной (uz2b.uz). ИП на налоге с оборота его не возвращает.
A16: Брокер, документы, сертификация | B16: 10000 | C16: сум за сумку | D16: Допущение: расходы на оформление партии, разделённые на число сумок в ней.
A18: Продажа
A19: Канал продаж | B19: Свой магазин | C19: выбор из списка | D19: «Свой магазин» — Telegram и Instagram с курьером. «Uzum Market» — комиссия и логистика маркетплейса.
A20: Средняя скидка от цены | B20: 0 | C20: % от цены | D20: 0% — продаём без скидок. Поставьте, например, 15%, чтобы увидеть эффект акций.
A21: Доставка клиентке по Ташкенту | B21: 30000 | C21: сум за заказ | D21: Допущение: курьер, бесплатно для клиентки. Для Uzum вместо неё берётся логистика Uzum.
A22: Доля отказов при осмотре | B22: 0.08 | C22: % заказов | D22: Допущение. Отказ = ещё одна поездка курьера впустую; сумка возвращается на склад.
A23: Налог с оборота (ИП) | B23: 0.01 | C23: % от выручки | D23: 1% при обороте до 1 млрд сум в год (buxgalter.uz, НК 2026). Выше — НДС и налог на прибыль.
A24: Комиссия за оплату (Click, Payme) | B24: 0.01 | C24: % от выручки | D24: Допущение. Для Uzum не применяется: оплата внутри маркетплейса.
A25: Реклама на один заказ (CAC) | B25: 70000 | C25: сум за заказ | D25: Допущение: таргет, блогеры, посевы в Telegram. Считайте фактическую по неделям.
A26: Комиссия Uzum Market | B26: 0.2 | C26: % от цены | D26: Допущение. Uzum берёт 3–35% в зависимости от категории (billz.io). Уточните в кабинете продавца.
A27: Логистика Uzum | B27: 8000 | C27: сум за заказ | D27: Около 8 000 сум за единицу (billz.io); зависит от размера товара.
A29: Постоянные расходы в месяц (полная загрузка)
A30: Контент: видеограф, героини, реквизит | B30: 8000000 | C30: сум в месяц | D30: Съёмки фильмов без слов, ASMR, фото.
A31: Менеджер заказов | B31: 5000000 | C31: сум в месяц | D31: Telegram, подтверждение заказов, курьеры.
A32: Хранение товара | B32: 1500000 | C32: сум в месяц | D32: Склад или кладовая.
A33: Сервисы: бот, сайт, учёт | B33: 500000 | C33: сум в месяц
A34: Бухгалтер на аутсорсе | B34: 1000000 | C34: сум в месяц
A35: Прочее | B35: 1000000 | C35: сум в месяц | D35: Связь, расходники, мелочи.
A36: Итого постоянные расходы | B36: =SUM(B30:B35) -> 17000000 | C36: сум в месяц | D36: Зарплаты основателей не включены.

Sheet Юнит-экономика
A1: Юнит-экономика: сколько остаётся с одной сумки
A2: Суммы в сумах на одну сумку (один заказ). Синие ячейки — ввод, чёрные — формулы, зелёные — ссылки на «Допущения».
A3: ="Канал продаж: "&Допущения!$B$19 -> Канал продаж: Свой магазин
A4: Показатель | B4: Ед. | C4: Выход и той | D4: Каждый день | E4: Спорт | F4: Мама | G4: Работа | H4: Средняя по долям | I4: Как считается
A5: Вводные по модели
A6: Закупка на фабрике | B6: ¥ | C6: 65 | D6: 95 | E6: 90 | F6: 100 | G6: 125 | H6: =SUMPRODUCT($C$8:$G$8,C6:G6) -> 95.25 | I6: Цена фабрики за 1 шт. без доставки. Пример — из бизнес-плана.
A7: Розничная цена | B7: сум | C7: 449000 | D7: 549000 | E7: 549000 | F7: 599000 | G7: 649000 | H7: =SUMPRODUCT($C$8:$G$8,C7:G7) -> 559000 | I7: Цена на витрине до скидки.
A8: Доля в продажах | B8: % | C8: 0.2 | D8: 0.25 | E8: 0.15 | F8: 0.2 | G8: 0.2 | H8: =SUM(C8:G8) -> 1 | I8: =IF(ABS(H8-1)>0.001,"Внимание: доли должны давать 100%, сейчас "&TEXT(H8,"0%"),"Доли в сумме 100% — всё верно") -> Доли в сумме 100% — всё верно
A9: Себестоимость в Ташкенте
A10: Закупка | B10: сум | C10: =C6*Допущения!$B$7 -> 107250 | D10: =D6*Допущения!$B$7 -> 156750 | E10: =E6*Допущения!$B$7 -> 148500 | F10: =F6*Допущения!$B$7 -> 165000 | G10: =G6*Допущения!$B$7 -> 206250 | H10: =SUMPRODUCT($C$8:$G$8,C10:G10) -> 157162.5 | I10: ¥ × курс юаня
A11: Байер | B11: сум | C11: =C10*Допущения!$B$10 -> 5362.5 | D11: =D10*Допущения!$B$10 -> 7837.5 | E11: =E10*Допущения!$B$10 -> 7425 | F11: =F10*Допущения!$B$10 -> 8250 | G11: =G10*Допущения!$B$10 -> 10312.5 | H11: =SUMPRODUCT($C$8:$G$8,C11:G11) -> 7858.125 | I11: закупка × комиссия байера
A12: Упаковка: пыльник, коробка, карточка | B12: сум | C12: =Допущения!$B$11*Допущения!$B$7 -> 23100 | D12: =Допущения!$B$11*Допущения!$B$7 -> 23100 | E12: =Допущения!$B$11*Допущения!$B$7 -> 23100 | F12: =Допущения!$B$11*Допущения!$B$7 -> 23100 | G12: =Допущения!$B$11*Допущения!$B$7 -> 23100 | H12: =SUMPRODUCT($C$8:$G$8,C12:G12) -> 23100 | I12: ¥ упаковки × курс юаня
A13: Доставка Китай → Ташкент | B13: сум | C13: =Допущения!$B$12*Допущения!$B$6 -> 40120 | D13: =Допущения!$B$12*Допущения!$B$6 -> 40120 | E13: =Допущения!$B$12*Допущения!$B$6 -> 40120 | F13: =Допущения!$B$12*Допущения!$B$6 -> 40120 | G13: =Допущения!$B$12*Допущения!$B$6 -> 40120 | H13: =SUMPRODUCT($C$8:$G$8,C13:G13) -> 40120 | I13: $ за сумку × курс доллара
A14: Таможенная стоимость (база для пошлины) | B14: сум | C14: =C10+C12+C13 -> 170470 | D14: =D10+D12+D13 -> 219970 | E14: =E10+E12+E13 -> 211720 | F14: =F10+F12+F13 -> 228220 | G14: =G10+G12+G13 -> 269470 | H14: =SUMPRODUCT($C$8:$G$8,C14:G14) -> 220382.5 | I14: справочно: закупка + упаковка + доставка; в итог не входит
A15: Пошлина | B15: сум | C15: =MAX(C14*Допущения!$B$13,Допущения!$B$14*Допущения!$B$6) -> 34094 | D15: =MAX(D14*Допущения!$B$13,Допущения!$B$14*Допущения!$B$6) -> 43994 | E15: =MAX(E14*Допущения!$B$13,Допущения!$B$14*Допущения!$B$6) -> 42344 | F15: =MAX(F14*Допущения!$B$13,Допущения!$B$14*Допущения!$B$6) -> 45644 | G15: =MAX(G14*Допущения!$B$13,Допущения!$B$14*Допущения!$B$6) -> 53894 | H15: =SUMPRODUCT($C$8:$G$8,C15:G15) -> 44076.5 | I15: большее из: тамож. стоимость × ставка или минимум $ за шт.
A16: НДС при ввозе | B16: сум | C16: =(C14+C15)*Допущения!$B$15 -> 24547.68 | D16: =(D14+D15)*Допущения!$B$15 -> 31675.68 | E16: =(E14+E15)*Допущения!$B$15 -> 30487.68 | F16: =(F14+F15)*Допущения!$B$15 -> 32863.68 | G16: =(G14+G15)*Допущения!$B$15 -> 38803.68 | H16: =SUMPRODUCT($C$8:$G$8,C16:G16) -> 31735.08 | I16: (тамож. стоимость + пошлина) × НДС
A17: Брокер, документы, сертификация | B17: сум | C17: =Допущения!$B$16 -> 10000 | D17: =Допущения!$B$16 -> 10000 | E17: =Допущения!$B$16 -> 10000 | F17: =Допущения!$B$16 -> 10000 | G17: =Допущения!$B$16 -> 10000 | H17: =SUMPRODUCT($C$8:$G$8,C17:G17) -> 10000 | I17: из «Допущений»
A18: Себестоимость сумки в Ташкенте | B18: сум | C18: =C10+C11+C12+C13+C15+C16+C17 -> 244474.18 | D18: =D10+D11+D12+D13+D15+D16+D17 -> 313477.18 | E18: =E10+E11+E12+E13+E15+E16+E17 -> 301976.68 | F18: =F10+F11+F12+F13+F15+F16+F17 -> 324977.68 | G18: =G10+G11+G12+G13+G15+G16+G17 -> 382480.18 | H18: =SUMPRODUCT($C$8:$G$8,C18:G18) -> 314052.21 | I18: сумма строк выше, кроме справочной
A19: Продажа одного заказа
A20: Цена после скидки | B20: сум | C20: =C7*(1-Допущения!$B$20) -> 449000 | D20: =D7*(1-Допущения!$B$20) -> 549000 | E20: =E7*(1-Допущения!$B$20) -> 549000 | F20: =F7*(1-Допущения!$B$20) -> 599000 | G20: =G7*(1-Допущения!$B$20) -> 649000 | H20: =SUMPRODUCT($C$8:$G$8,C20:G20) -> 559000 | I20: розничная цена × (1 − скидка)
A21: Доставка клиентке | B21: сум | C21: =IF(Допущения!$B$19="Uzum Market",Допущения!$B$27,Допущения!$B$21) -> 30000 | D21: =IF(Допущения!$B$19="Uzum Market",Допущения!$B$27,Допущения!$B$21) -> 30000 | E21: =IF(Допущения!$B$19="Uzum Market",Допущения!$B$27,Допущения!$B$21) -> 30000 | F21: =IF(Допущения!$B$19="Uzum Market",Допущения!$B$27,Допущения!$B$21) -> 30000 | G21: =IF(Допущения!$B$19="Uzum Market",Допущения!$B$27,Допущения!$B$21) -> 30000 | H21: =SUMPRODUCT($C$8:$G$8,C21:G21) -> 30000 | I21: свой магазин — курьер; Uzum — логистика маркетплейса
A22: Отказы при осмотре | B22: сум | C22: =C21*Допущения!$B$22 -> 2400 | D22: =D21*Допущения!$B$22 -> 2400 | E22: =E21*Допущения!$B$22 -> 2400 | F22: =F21*Допущения!$B$22 -> 2400 | G22: =G21*Допущения!$B$22 -> 2400 | H22: =SUMPRODUCT($C$8:$G$8,C22:G22) -> 2400 | I22: доставка × доля отказов: лишние поездки на каждый заказ
A23: Налог с оборота | B23: сум | C23: =C20*Допущения!$B$23 -> 4490 | D23: =D20*Допущения!$B$23 -> 5490 | E23: =E20*Допущения!$B$23 -> 5490 | F23: =F20*Допущения!$B$23 -> 5990 | G23: =G20*Допущения!$B$23 -> 6490 | H23: =SUMPRODUCT($C$8:$G$8,C23:G23) -> 5590 | I23: цена после скидки × ставка
A24: Комиссия за оплату | B24: сум | C24: =IF(Допущения!$B$19="Uzum Market",0,C20*Допущения!$B$24) -> 4490 | D24: =IF(Допущения!$B$19="Uzum Market",0,D20*Допущения!$B$24) -> 5490 | E24: =IF(Допущения!$B$19="Uzum Market",0,E20*Допущения!$B$24) -> 5490 | F24: =IF(Допущения!$B$19="Uzum Market",0,F20*Допущения!$B$24) -> 5990 | G24: =IF(Допущения!$B$19="Uzum Market",0,G20*Допущения!$B$24) -> 6490 | H24: =SUMPRODUCT($C$8:$G$8,C24:G24) -> 5590 | I24: Click, Payme; на Uzum — 0
A25: Комиссия маркетплейса | B25: сум | C25: =IF(Допущения!$B$19="Uzum Market",C20*Допущения!$B$26,0) -> 0 | D25: =IF(Допущения!$B$19="Uzum Market",D20*Допущения!$B$26,0) -> 0 | E25: =IF(Допущения!$B$19="Uzum Market",E20*Допущения!$B$26,0) -> 0 | F25: =IF(Допущения!$B$19="Uzum Market",F20*Допущения!$B$26,0) -> 0 | G25: =IF(Допущения!$B$19="Uzum Market",G20*Допущения!$B$26,0) -> 0 | H25: =SUMPRODUCT($C$8:$G$8,C25:G25) -> 0 | I25: только для Uzum Market
A26: Реклама на один заказ | B26: сум | C26: =Допущения!$B$25 -> 70000 | D26: =Допущения!$B$25 -> 70000 | E26: =Допущения!$B$25 -> 70000 | F26: =Допущения!$B$25 -> 70000 | G26: =Допущения!$B$25 -> 70000 | H26: =SUMPRODUCT($C$8:$G$8,C26:G26) -> 70000 | I26: из «Допущений»
A27: Расходы на продажу | B27: сум | C27: =SUM(C21:C26) -> 111380 | D27: =SUM(D21:D26) -> 113380 | E27: =SUM(E21:E26) -> 113380 | F27: =SUM(F21:F26) -> 114380 | G27: =SUM(G21:G26) -> 115380 | H27: =SUMPRODUCT($C$8:$G$8,C27:G27) -> 113580 | I27: сумма строк выше
A28: Результат
A29: Остаётся с заказа | B29: сум | C29: =C20-C18-C27 -> 93145.82 | D29: =D20-D18-D27 -> 122142.82 | E29: =E20-E18-E27 -> 133643.32 | F29: =F20-F18-F27 -> 159642.32 | G29: =G20-G18-G27 -> 151139.82 | H29: =SUMPRODUCT($C$8:$G$8,C29:G29) -> 131367.8 | I29: цена после скидки − себестоимость − расходы на продажу; до постоянных расходов
A30: Доля от цены | B30: % | C30: =IFERROR(C29/C20,0) -> 0.20745171 | D30: =IFERROR(D29/D20,0) -> 0.22248237 | E30: =IFERROR(E29/E20,0) -> 0.24343046 | F30: =IFERROR(F29/F20,0) -> 0.26651472 | G30: =IFERROR(G29/G20,0) -> 0.23288108 | H30: =IFERROR(H29/H20,0) -> 0.235005 | I30: остаётся с заказа / цена после скидки
A31: Наценка: цена / себестоимость | B31: раз | C31: =IFERROR(C20/C18,0) -> 1.8365948 | D31: =IFERROR(D20/D18,0) -> 1.7513237 | E31: =IFERROR(E20/E18,0) -> 1.8180212 | F31: =IFERROR(F20/F18,0) -> 1.8432035 | G31: =IFERROR(G20/G18,0) -> 1.69682 | H31: =IFERROR(H20/H18,0) -> 1.7799588 | I31: в моде обычно нужна наценка от 2 раз, чтобы покрыть продажу и рекламу
A32: Предельная реклама на заказ | B32: сум | C32: =C29+C26 -> 163145.82 | D32: =D29+D26 -> 192142.82 | E32: =E29+E26 -> 203643.32 | F32: =F29+F26 -> 229642.32 | G32: =G29+G26 -> 221139.82 | H32: =SUMPRODUCT($C$8:$G$8,C32:G32) -> 201367.8 | I32: при такой рекламе на заказ модель выходит в ноль
A33: Минимальная розничная цена | B33: сум | C33: =IFERROR((C18+C21+C22+C26)/(1-(C23+C24+C25)/C20)/(1-Допущения!$B$20),0) -> 353953.24 | D33: =IFERROR((D18+D21+D22+D26)/(1-(D23+D24+D25)/D20)/(1-Допущения!$B$20),0) -> 424364.47 | E33: =IFERROR((E18+E21+E22+E26)/(1-(E23+E24+E25)/E20)/(1-Допущения!$B$20),0) -> 412629.27 | F33: =IFERROR((F18+F21+F22+F26)/(1-(F23+F24+F25)/F20)/(1-Допущения!$B$20),0) -> 436099.67 | G33: =IFERROR((G18+G21+G22+G26)/(1-(G23+G24+G25)/G20)/(1-Допущения!$B$20),0) -> 494775.69 | H33: =SUMPRODUCT($C$8:$G$8,C33:G33) -> 424951.23 | I33: цена до скидки, при которой с заказа остаётся 0 (без постоянных расходов)
A35: Безубыточность
A36: Постоянные расходы в месяц | B36: сум | C36: =Допущения!$B$36 -> 17000000 | I36: из «Допущений»
A37: Точка безубыточности | B37: заказов в мес. | C37: =IF(H29<=0,"убыток с каждого заказа",C36/H29) -> 129.40767 | I37: постоянные расходы / средний доход с заказа (колонка H)
A38: То же в день | B38: заказов в день | C38: =IF(ISNUMBER(C37),C37/30,"—") -> 4.3135889 | I38: при 30 днях в месяце

Sheet Прогноз
A1: Прогноз на 12 месяцев: заказы → прибыль
A2: Вводите заказы и постоянные расходы по месяцам (синие ячейки). Доход с заказа берётся из колонки «Средняя» листа «Юнит-экономика».
A4: Показатель, сум | B4: янв 2027 | C4: фев 2027 | D4: мар 2027 | E4: апр 2027 | F4: май 2027 | G4: июн 2027 | H4: июл 2027 | I4: авг 2027 | J4: сен 2027 | K4: окт 2027 | L4: ноя 2027 | M4: дек 2027 | N4: Итого за год
A5: Заказов в месяц | B5: 40 | C5: 70 | D5: 150 | E5: 100 | F5: 120 | G5: 130 | H5: 120 | I5: 140 | J5: 160 | K5: 180 | L5: 200 | M5: 260 | N5: =SUM(B5:M5) -> 1670
A6: Постоянные расходы | B6: 10000000 | C6: 10000000 | D6: 10000000 | E6: 14000000 | F6: 14000000 | G6: 14000000 | H6: 17000000 | I6: 17000000 | J6: 17000000 | K6: 17000000 | L6: 17000000 | M6: 17000000 | N6: =SUM(B6:M6) -> 174000000
A8: Выручка | B8: =B5*'Юнит-экономика'!$H$20 -> 22360000 | C8: =C5*'Юнит-экономика'!$H$20 -> 39130000 | D8: =D5*'Юнит-экономика'!$H$20 -> 83850000 | E8: =E5*'Юнит-экономика'!$H$20 -> 55900000 | F8: =F5*'Юнит-экономика'!$H$20 -> 67080000 | G8: =G5*'Юнит-экономика'!$H$20 -> 72670000 | H8: =H5*'Юнит-экономика'!$H$20 -> 67080000 | I8: =I5*'Юнит-экономика'!$H$20 -> 78260000 | ... M8: =M5*'Юнит-экономика'!$H$20 -> 145340000 | N8: =SUM(B8:M8) -> 933530000
A9: Себестоимость проданных сумок | B9: =B5*'Юнит-экономика'!$H$18 -> 12562088 | C9: =C5*'Юнит-экономика'!$H$18 -> 21983654 | D9: =D5*'Юнит-экономика'!$H$18 -> 47107831 | E9: =E5*'Юнит-экономика'!$H$18 -> 31405220 | F9: =F5*'Юнит-экономика'!$H$18 -> 37686265 | G9: =G5*'Юнит-экономика'!$H$18 -> 40826787 | H9: =H5*'Юнит-экономика'!$H$18 -> 37686265 | I9: =I5*'Юнит-экономика'!$H$18 -> 43967309 | ... M9: =M5*'Юнит-экономика'!$H$18 -> 81653573 | N9: =SUM(B9:M9) -> 5.2446718e+08
A10: Расходы на продажу (доставка, налог, реклама…) | B10: =B5*'Юнит-экономика'!$H$27 -> 4543200 | C10: =C5*'Юнит-экономика'!$H$27 -> 7950600 | D10: =D5*'Юнит-экономика'!$H$27 -> 17037000 | E10: =E5*'Юнит-экономика'!$H$27 -> 11358000 | F10: =F5*'Юнит-экономика'!$H$27 -> 13629600 | G10: =G5*'Юнит-экономика'!$H$27 -> 14765400 | H10: =H5*'Юнит-экономика'!$H$27 -> 13629600 | I10: =I5*'Юнит-экономика'!$H$27 -> 15901200 | ... M10: =M5*'Юнит-экономика'!$H$27 -> 29530800 | N10: =SUM(B10:M10) -> 189678600
A11: Остаётся с заказов | B11: =B8-B9-B10 -> 5254711.8 | C11: =C8-C9-C10 -> 9195745.7 | D11: =D8-D9-D10 -> 19705169 | E11: =E8-E9-E10 -> 13136780 | F11: =F8-F9-F10 -> 15764135 | G11: =G8-G9-G10 -> 17077813 | H11: =H8-H9-H10 -> 15764135 | I11: =I8-I9-I10 -> 18391491 | ... M11: =M8-M9-M10 -> 34155627 | N11: =SUM(B11:M11) -> 2.1938422e+08
A12: Операционная прибыль | B12: =B11-B6 -> -4745288.2 | C12: =C11-C6 -> -804254.35 | D12: =D11-D6 -> 9705169.2 | E12: =E11-E6 -> -863220.5 | F12: =F11-F6 -> 1764135.4 | G12: =G11-G6 -> 3077813.4 | H12: =H11-H6 -> -1235864.6 | I12: =I11-I6 -> 1391491.3 | ... M12: =M11-M6 -> 17155627 | N12: =SUM(B12:M12) -> 45384218
A13: Накопленная операционная прибыль | B13: =B12 -> -4745288.2 | C13: =B13+C12 -> -5549542.5 | D13: =C13+D12 -> 4155626.7 | E13: =D13+E12 -> 3292406.2 | F13: =E13+F12 -> 5056541.6 | G13: =F13+G12 -> 8134355 | H13: =G13+H12 -> 6898490.3 | I13: =H13+I12 -> 8289981.6 | J13: =I13+J12 -> 12308829 | ... M13: =L13+M12 -> 45384218
A15: Месяцев с прибылью | B15: =COUNTIF(B12:M12,">0") -> 8
A16: Оборот за год против порога налога с оборота | B16: =IF(N8>1000000000,"Оборот выше 1 млрд сум — с месяца превышения ИП платит НДС и налог на прибыль","Оборот до 1 млрд сум — налог с оборота 1%") -> Оборот до 1 млрд сум — налог с оборота 1%
A18: Стартовые вложения (до запуска) | B18: сум
A19: Образцы: около 15 шт. с экспресс-доставкой | B19: 6500000
A20: Бренд: имя, логотип, дизайн упаковки | B20: 6000000
A21: Регистрация ИП, брокер, резерв на сертификацию | B21: 6000000
A22: Telegram-бот и сайт-каталог | B22: 4000000
A23: Запускная съёмка пяти сценариев | B23: 18000000
A24: Реклама и блогеры до запуска | B24: 10000000
A25: Вложения без товара | B25: =SUM(B19:B24) -> 50500000
A26: Первая партия, шт. | B26: 200
A27: Первая партия, сум | B27: =B26*'Юнит-экономика'!$H$18 -> 62810441 | C27: шт. × средняя себестоимость
A28: Всего до запуска | B28: =B25+B27 -> 113310441
A30: Результат с учётом вложений без товара | B30: =B13-$B$25 -> -55245288 | C30: =C13-$B$25 -> -56049543 | D30: =D13-$B$25 -> -46344373 | E30: =E13-$B$25 -> -47207594 | F30: =F13-$B$25 -> -45443458 | G30: =G13-$B$25 -> -42365645 | H30: =H13-$B$25 -> -43601510 | I30: =I13-$B$25 -> -42210018 | ... M30: =M13-$B$25 -> -5115782.4
A31: служебная строка: номер месяца, если результат ≥ 0 | B31: =IF(B30>=0,1,99) -> 99 | C31: =IF(C30>=0,2,99) -> 99 | D31: =IF(D30>=0,3,99) -> 99 | E31: =IF(E30>=0,4,99) -> 99 | F31: =IF(F30>=0,5,99) -> 99 | G31: =IF(G30>=0,6,99) -> 99 | H31: =IF(H30>=0,7,99) -> 99 | I31: =IF(I30>=0,8,99) -> 99 | J31: =IF(J30>=0,9,99) -> 99 | K31: =IF(K30>=0,10,99) -> 99 | L31: =IF(L30>=0,11,99) -> 99 | M31: =IF(M30>=0,12,99) -> 99
A32: Окупаемость вложений без товара | B32: =IF(MIN(B31:M31)=99,"позже 12 месяцев",INDEX(B4:M4,MIN(B31:M31))) -> позже 12 месяцев | C32: Товар на складе не считаем расходом: это деньги, которые вернутся с продажами.

Sheet Чувствительность
A1: Точка безубыточности: заказов в месяц
A2: Как меняется нужное число заказов, если сдвинуть цену (столбцы) и стоимость рекламы на заказ (строки). Постоянные расходы — из «Допущений».
A4: Средняя цена после скидки | B4: ='Юнит-экономика'!$H$20 -> 559000
A5: Средняя себестоимость в Ташкенте | B5: ='Юнит-экономика'!$H$18 -> 314052.21
A6: Доставка и отказы на заказ | B6: ='Юнит-экономика'!$H$21+'Юнит-экономика'!$H$22 -> 32400
A7: Налоги и комиссии, % от цены | B7: =IFERROR(('Юнит-экономика'!$H$23+'Юнит-экономика'!$H$24+'Юнит-экономика'!$H$25)/'Юнит-экономика'!$H$20,0) -> 0.02
A8: Постоянные расходы в месяц | B8: =Допущения!$B$36 -> 17000000
A10: Реклама на заказ, сум ↓ / цена → | B10: -0.2 | C10: -0.15 | D10: -0.1 | E10: -0.05 | F10: 0 | G10: 0.05 | H10: 0.1 | I10: 0.15 | J10: 0.2
A11: 40000 | B11: =IF(($B$4*(1+B$10)*(1-$B$7)-$B$5-$B$6-$A11)<=0,"убыток",$B$8/($B$4*(1+B$10)*(1-$B$7)-$B$5-$B$6-$A11)) -> 328.16129 | C11: =IF(($B$4*(1+C$10)*(1-$B$7)-$B$5-$B$6-$A11)<=0,"убыток",$B$8/($B$4*(1+C$10)*(1-$B$7)-$B$5-$B$6-$A11)) -> 214.66057 | D11: =IF(($B$4*(1+D$10)*(1-$B$7)-$B$5-$B$6-$A11)<=0,"убыток",$B$8/($B$4*(1+D$10)*(1-$B$7)-$B$5-$B$6-$A11)) -> 159.49593 | E11: =IF(($B$4*(1+E$10)*(1-$B$7)-$B$5-$B$6-$A11)<=0,"убыток",$B$8/($B$4*(1+E$10)*(1-$B$7)-$B$5-$B$6-$A11)) -> 126.88764 | F11: =IF(($B$4*(1+F$10)*(1-$B$7)-$B$5-$B$6-$A11)<=0,"убыток",$B$8/($B$4*(1+F$10)*(1-$B$7)-$B$5-$B$6-$A11)) -> 105.3494 | G11: =IF(($B$4*(1+G$10)*(1-$B$7)-$B$5-$B$6-$A11)<=0,"убыток",$B$8/($B$4*(1+G$10)*(1-$B$7)-$B$5-$B$6-$A11)) -> 90.062029 | H11: =IF(($B$4*(1+H$10)*(1-$B$7)-$B$5-$B$6-$A11)<=0,"убыток",$B$8/($B$4*(1+H$10)*(1-$B$7)-$B$5-$B$6-$A11)) -> 78.649161 | I11: =IF(($B$4*(1+I$10)*(1-$B$7)-$B$5-$B$6-$A11)<=0,"убыток",$B$8/($B$4*(1+I$10)*(1-$B$7)-$B$5-$B$6-$A11)) -> 69.8035 | J11: =IF(($B$4*(1+J$10)*(1-$B$7)-$B$5-$B$6-$A11)<=0,"убыток",$B$8/($B$4*(1+J$10)*(1-$B$7)-$B$5-$B$6-$A11)) -> 62.746419
A12: 50000 | B12: =IF(($B$4*(1+B$10)*(1-$B$7)-$B$5-$B$6-$A12)<=0,"убыток",$B$8/($B$4*(1+B$10)*(1-$B$7)-$B$5-$B$6-$A12)) -> 406.66164 | C12: =IF(($B$4*(1+C$10)*(1-$B$7)-$B$5-$B$6-$A12)<=0,"убыток",$B$8/($B$4*(1+C$10)*(1-$B$7)-$B$5-$B$6-$A12)) -> 245.68322 | D12: =IF(($B$4*(1+D$10)*(1-$B$7)-$B$5-$B$6-$A12)<=0,"убыток",$B$8/($B$4*(1+D$10)*(1-$B$7)-$B$5-$B$6-$A12)) -> 176.00932 | E12: =IF(($B$4*(1+E$10)*(1-$B$7)-$B$5-$B$6-$A12)<=0,"убыток",$B$8/($B$4*(1+E$10)*(1-$B$7)-$B$5-$B$6-$A12)) -> 137.12243 | F12: =IF(($B$4*(1+F$10)*(1-$B$7)-$B$5-$B$6-$A12)<=0,"убыток",$B$8/($B$4*(1+F$10)*(1-$B$7)-$B$5-$B$6-$A12)) -> 112.30923 | G12: =IF(($B$4*(1+G$10)*(1-$B$7)-$B$5-$B$6-$A12)<=0,"убыток",$B$8/($B$4*(1+G$10)*(1-$B$7)-$B$5-$B$6-$A12)) -> 95.100216 | H12: =IF(($B$4*(1+H$10)*(1-$B$7)-$B$5-$B$6-$A12)<=0,"убыток",$B$8/($B$4*(1+H$10)*(1-$B$7)-$B$5-$B$6-$A12)) -> 82.464307 | I12: =IF(($B$4*(1+I$10)*(1-$B$7)-$B$5-$B$6-$A12)<=0,"убыток",$B$8/($B$4*(1+I$10)*(1-$B$7)-$B$5-$B$6-$A12)) -> 72.792422 | J12: =IF(($B$4*(1+J$10)*(1-$B$7)-$B$5-$B$6-$A12)<=0,"убыток",$B$8/($B$4*(1+J$10)*(1-$B$7)-$B$5-$B$6-$A12)) -> 65.151125
A13: 60000 | B13: =IF(($B$4*(1+B$10)*(1-$B$7)-$B$5-$B$6-$A13)<=0,"убыток",$B$8/($B$4*(1+B$10)*(1-$B$7)-$B$5-$B$6-$A13)) -> 534.5274 | C13: =IF(($B$4*(1+C$10)*(1-$B$7)-$B$5-$B$6-$A13)<=0,"убыток",$B$8/($B$4*(1+C$10)*(1-$B$7)-$B$5-$B$6-$A13)) -> 287.18741 | D13: =IF(($B$4*(1+D$10)*(1-$B$7)-$B$5-$B$6-$A13)<=0,"убыток",$B$8/($B$4*(1+D$10)*(1-$B$7)-$B$5-$B$6-$A13)) -> 196.33706 | E13: =IF(($B$4*(1+E$10)*(1-$B$7)-$B$5-$B$6-$A13)<=0,"убыток",$B$8/($B$4*(1+E$10)*(1-$B$7)-$B$5-$B$6-$A13)) -> 149.15317 | F13: =IF(($B$4*(1+F$10)*(1-$B$7)-$B$5-$B$6-$A13)<=0,"убыток",$B$8/($B$4*(1+F$10)*(1-$B$7)-$B$5-$B$6-$A13)) -> 120.2537 | G13: =IF(($B$4*(1+G$10)*(1-$B$7)-$B$5-$B$6-$A13)<=0,"убыток",$B$8/($B$4*(1+G$10)*(1-$B$7)-$B$5-$B$6-$A13)) -> 100.73549 | H13: =IF(($B$4*(1+H$10)*(1-$B$7)-$B$5-$B$6-$A13)<=0,"убыток",$B$8/($B$4*(1+H$10)*(1-$B$7)-$B$5-$B$6-$A13)) -> 86.668457 | I13: =IF(($B$4*(1+I$10)*(1-$B$7)-$B$5-$B$6-$A13)<=0,"убыток",$B$8/($B$4*(1+I$10)*(1-$B$7)-$B$5-$B$6-$A13)) -> 76.048759 | J13: =IF(($B$4*(1+J$10)*(1-$B$7)-$B$5-$B$6-$A13)<=0,"убыток",$B$8/($B$4*(1+J$10)*(1-$B$7)-$B$5-$B$6-$A13)) -> 67.747493
A14: 70000 | B14: =IF(($B$4*(1+B$10)*(1-$B$7)-$B$5-$B$6-$A14)<=0,"убыток",$B$8/($B$4*(1+B$10)*(1-$B$7)-$B$5-$B$6-$A14)) -> 779.68078 | C14: =IF(($B$4*(1+C$10)*(1-$B$7)-$B$5-$B$6-$A14)<=0,"убыток",$B$8/($B$4*(1+C$10)*(1-$B$7)-$B$5-$B$6-$A14)) -> 345.56501 | D14: =IF(($B$4*(1+D$10)*(1-$B$7)-$B$5-$B$6-$A14)<=0,"убыток",$B$8/($B$4*(1+D$10)*(1-$B$7)-$B$5-$B$6-$A14)) -> 221.97328 | E14: =IF(($B$4*(1+E$10)*(1-$B$7)-$B$5-$B$6-$A14)<=0,"убыток",$B$8/($B$4*(1+E$10)*(1-$B$7)-$B$5-$B$6-$A14)) -> 163.49802 | F14: =IF(($B$4*(1+F$10)*(1-$B$7)-$B$5-$B$6-$A14)<=0,"убыток",$B$8/($B$4*(1+F$10)*(1-$B$7)-$B$5-$B$6-$A14)) -> 129.40767 | G14: =IF(($B$4*(1+G$10)*(1-$B$7)-$B$5-$B$6-$A14)<=0,"убыток",$B$8/($B$4*(1+G$10)*(1-$B$7)-$B$5-$B$6-$A14)) -> 107.08068 | H14: =IF(($B$4*(1+H$10)*(1-$B$7)-$B$5-$B$6-$A14)<=0,"убыток",$B$8/($B$4*(1+H$10)*(1-$B$7)-$B$5-$B$6-$A14)) -> 91.324301 | I14: =IF(($B$4*(1+I$10)*(1-$B$7)-$B$5-$B$6-$A14)<=0,"убыток",$B$8/($B$4*(1+I$10)*(1-$B$7)-$B$5-$B$6-$A14)) -> 79.610081 | J14: =IF(($B$4*(1+J$10)*(1-$B$7)-$B$5-$B$6-$A14)<=0,"убыток",$B$8/($B$4*(1+J$10)*(1-$B$7)-$B$5-$B$6-$A14)) -> 70.559388
A15: 80000 | B15: =IF(($B$4*(1+B$10)*(1-$B$7)-$B$5-$B$6-$A15)<=0,"убыток",$B$8/($B$4*(1+B$10)*(1-$B$7)-$B$5-$B$6-$A15)) -> 1440.2148 | C15: =IF(($B$4*(1+C$10)*(1-$B$7)-$B$5-$B$6-$A15)<=0,"убыток",$B$8/($B$4*(1+C$10)*(1-$B$7)-$B$5-$B$6-$A15)) -> 433.73106 | D15: =IF(($B$4*(1+D$10)*(1-$B$7)-$B$5-$B$6-$A15)<=0,"убыток",$B$8/($B$4*(1+D$10)*(1-$B$7)-$B$5-$B$6-$A15)) -> 255.30971 | E15: =IF(($B$4*(1+E$10)*(1-$B$7)-$B$5-$B$6-$A15)<=0,"убыток",$B$8/($B$4*(1+E$10)*(1-$B$7)-$B$5-$B$6-$A15)) -> 180.89572 | F15: =IF(($B$4*(1+F$10)*(1-$B$7)-$B$5-$B$6-$A15)<=0,"убыток",$B$8/($B$4*(1+F$10)*(1-$B$7)-$B$5-$B$6-$A15)) -> 140.07011 | G15: =IF(($B$4*(1+G$10)*(1-$B$7)-$B$5-$B$6-$A15)<=0,"убыток",$B$8/($B$4*(1+G$10)*(1-$B$7)-$B$5-$B$6-$A15)) -> 114.27896 | H15: =IF(($B$4*(1+H$10)*(1-$B$7)-$B$5-$B$6-$A15)<=0,"убыток",$B$8/($B$4*(1+H$10)*(1-$B$7)-$B$5-$B$6-$A15)) -> 96.50877 | I15: =IF(($B$4*(1+I$10)*(1-$B$7)-$B$5-$B$6-$A15)<=0,"убыток",$B$8/($B$4*(1+I$10)*(1-$B$7)-$B$5-$B$6-$A15)) -> 83.52134 | J15: =IF(($B$4*(1+J$10)*(1-$B$7)-$B$5-$B$6-$A15)<=0,"убыток",$B$8/($B$4*(1+J$10)*(1-$B$7)-$B$5-$B$6-$A15)) -> 73.614809
A16: 90000 | B16: =IF(($B$4*(1+B$10)*(1-$B$7)-$B$5-$B$6-$A16)<=0,"убыток",$B$8/($B$4*(1+B$10)*(1-$B$7)-$B$5-$B$6-$A16)) -> 9424.5743 | C16: =IF(($B$4*(1+C$10)*(1-$B$7)-$B$5-$B$6-$A16)<=0,"убыток",$B$8/($B$4*(1+C$10)*(1-$B$7)-$B$5-$B$6-$A16)) -> 582.29558 | D16: =IF(($B$4*(1+D$10)*(1-$B$7)-$B$5-$B$6-$A16)<=0,"убыток",$B$8/($B$4*(1+D$10)*(1-$B$7)-$B$5-$B$6-$A16)) -> 300.42876 | E16: =IF(($B$4*(1+E$10)*(1-$B$7)-$B$5-$B$6-$A16)<=0,"убыток",$B$8/($B$4*(1+E$10)*(1-$B$7)-$B$5-$B$6-$A16)) -> 202.43688 | F16: =IF(($B$4*(1+F$10)*(1-$B$7)-$B$5-$B$6-$A16)<=0,"убыток",$B$8/($B$4*(1+F$10)*(1-$B$7)-$B$5-$B$6-$A16)) -> 152.64736 | G16: =IF(($B$4*(1+G$10)*(1-$B$7)-$B$5-$B$6-$A16)<=0,"убыток",$B$8/($B$4*(1+G$10)*(1-$B$7)-$B$5-$B$6-$A16)) -> 122.51476 | H16: =IF(($B$4*(1+H$10)*(1-$B$7)-$B$5-$B$6-$A16)<=0,"убыток",$B$8/($B$4*(1+H$10)*(1-$B$7)-$B$5-$B$6-$A16)) -> 102.31731 | I16: =IF(($B$4*(1+I$10)*(1-$B$7)-$B$5-$B$6-$A16)<=0,"убыток",$B$8/($B$4*(1+I$10)*(1-$B$7)-$B$5-$B$6-$A16)) -> 87.836779 | J16: =IF(($B$4*(1+J$10)*(1-$B$7)-$B$5-$B$6-$A16)<=0,"убыток",$B$8/($B$4*(1+J$10)*(1-$B$7)-$B$5-$B$6-$A16)) -> 76.946824
A17: 100000 | B17: =IF(($B$4*(1+B$10)*(1-$B$7)-$B$5-$B$6-$A17)<=0,"убыток",$B$8/($B$4*(1+B$10)*(1-$B$7)-$B$5-$B$6-$A17)) -> убыток | C17: =IF(($B$4*(1+C$10)*(1-$B$7)-$B$5-$B$6-$A17)<=0,"убыток",$B$8/($B$4*(1+C$10)*(1-$B$7)-$B$5-$B$6-$A17)) -> 885.65676 | D17: =IF(($B$4*(1+D$10)*(1-$B$7)-$B$5-$B$6-$A17)<=0,"убыток",$B$8/($B$4*(1+D$10)*(1-$B$7)-$B$5-$B$6-$A17)) -> 364.9181 | E17: =IF(($B$4*(1+E$10)*(1-$B$7)-$B$5-$B$6-$A17)<=0,"убыток",$B$8/($B$4*(1+E$10)*(1-$B$7)-$B$5-$B$6-$A17)) -> 229.80179 | F17: =IF(($B$4*(1+F$10)*(1-$B$7)-$B$5-$B$6-$A17)<=0,"убыток",$B$8/($B$4*(1+F$10)*(1-$B$7)-$B$5-$B$6-$A17)) -> 167.70612 | G17: =IF(($B$4*(1+G$10)*(1-$B$7)-$B$5-$B$6-$A17)<=0,"убыток",$B$8/($B$4*(1+G$10)*(1-$B$7)-$B$5-$B$6-$A17)) -> 132.02982 | H17: =IF(($B$4*(1+H$10)*(1-$B$7)-$B$5-$B$6-$A17)<=0,"убыток",$B$8/($B$4*(1+H$10)*(1-$B$7)-$B$5-$B$6-$A17)) -> 108.86982 | I17: =IF(($B$4*(1+I$10)*(1-$B$7)-$B$5-$B$6-$A17)<=0,"убыток",$B$8/($B$4*(1+I$10)*(1-$B$7)-$B$5-$B$6-$A17)) -> 92.62246 | J17: =IF(($B$4*(1+J$10)*(1-$B$7)-$B$5-$B$6-$A17)<=0,"убыток",$B$8/($B$4*(1+J$10)*(1-$B$7)-$B$5-$B$6-$A17)) -> 80.594772
A18: 110000 | B18: =IF(($B$4*(1+B$10)*(1-$B$7)-$B$5-$B$6-$A18)<=0,"убыток",$B$8/($B$4*(1+B$10)*(1-$B$7)-$B$5-$B$6-$A18)) -> убыток | C18: =IF(($B$4*(1+C$10)*(1-$B$7)-$B$5-$B$6-$A18)<=0,"убыток",$B$8/($B$4*(1+C$10)*(1-$B$7)-$B$5-$B$6-$A18)) -> 1848.8721 | D18: =IF(($B$4*(1+D$10)*(1-$B$7)-$B$5-$B$6-$A18)<=0,"убыток",$B$8/($B$4*(1+D$10)*(1-$B$7)-$B$5-$B$6-$A18)) -> 464.66122 | E18: =IF(($B$4*(1+E$10)*(1-$B$7)-$B$5-$B$6-$A18)<=0,"убыток",$B$8/($B$4*(1+E$10)*(1-$B$7)-$B$5-$B$6-$A18)) -> 265.72134 | F18: =IF(($B$4*(1+F$10)*(1-$B$7)-$B$5-$B$6-$A18)<=0,"убыток",$B$8/($B$4*(1+F$10)*(1-$B$7)-$B$5-$B$6-$A18)) -> 186.06118 | G18: =IF(($B$4*(1+G$10)*(1-$B$7)-$B$5-$B$6-$A18)<=0,"убыток",$B$8/($B$4*(1+G$10)*(1-$B$7)-$B$5-$B$6-$A18)) -> 143.14729 | H18: =IF(($B$4*(1+H$10)*(1-$B$7)-$B$5-$B$6-$A18)<=0,"убыток",$B$8/($B$4*(1+H$10)*(1-$B$7)-$B$5-$B$6-$A18)) -> 116.31901 | I18: =IF(($B$4*(1+I$10)*(1-$B$7)-$B$5-$B$6-$A18)<=0,"убыток",$B$8/($B$4*(1+I$10)*(1-$B$7)-$B$5-$B$6-$A18)) -> 97.959676 | J18: =IF(($B$4*(1+J$10)*(1-$B$7)-$B$5-$B$6-$A18)<=0,"убыток",$B$8/($B$4*(1+J$10)*(1-$B$7)-$B$5-$B$6-$A18)) -> 84.605824
A19: 120000 | B19: =IF(($B$4*(1+B$10)*(1-$B$7)-$B$5-$B$6-$A19)<=0,"убыток",$B$8/($B$4*(1+B$10)*(1-$B$7)-$B$5-$B$6-$A19)) -> убыток | C19: =IF(($B$4*(1+C$10)*(1-$B$7)-$B$5-$B$6-$A19)<=0,"убыток",$B$8/($B$4*(1+C$10)*(1-$B$7)-$B$5-$B$6-$A19)) -> убыток | D19: =IF(($B$4*(1+D$10)*(1-$B$7)-$B$5-$B$6-$A19)<=0,"убыток",$B$8/($B$4*(1+D$10)*(1-$B$7)-$B$5-$B$6-$A19)) -> 639.43922 | E19: =IF(($B$4*(1+E$10)*(1-$B$7)-$B$5-$B$6-$A19)<=0,"убыток",$B$8/($B$4*(1+E$10)*(1-$B$7)-$B$5-$B$6-$A19)) -> 314.95016 | F19: =IF(($B$4*(1+F$10)*(1-$B$7)-$B$5-$B$6-$A19)<=0,"убыток",$B$8/($B$4*(1+F$10)*(1-$B$7)-$B$5-$B$6-$A19)) -> 208.92787 | G19: =IF(($B$4*(1+G$10)*(1-$B$7)-$B$5-$B$6-$A19)<=0,"убыток",$B$8/($B$4*(1+G$10)*(1-$B$7)-$B$5-$B$6-$A19)) -> 156.3092 | H19: =IF(($B$4*(1+H$10)*(1-$B$7)-$B$5-$B$6-$A19)<=0,"убыток",$B$8/($B$4*(1+H$10)*(1-$B$7)-$B$5-$B$6-$A19)) -> 124.86247 | I19: =IF(($B$4*(1+I$10)*(1-$B$7)-$B$5-$B$6-$A19)<=0,"убыток",$B$8/($B$4*(1+I$10)*(1-$B$7)-$B$5-$B$6-$A19)) -> 103.9496 | J19: =IF(($B$4*(1+J$10)*(1-$B$7)-$B$5-$B$6-$A19)<=0,"убыток",$B$8/($B$4*(1+J$10)*(1-$B$7)-$B$5-$B$6-$A19)) -> 89.03703
A21: Столбец «0%» и строка с текущей рекламой из «Допущений» — базовый расчёт. Зелёное — меньше заказов нужно, красное — больше.
A22: Цифры в заголовках (сдвиг цены и реклама) можно менять.
